{
    "stopReasonsList": [
        {
            "code": 1,
            "description": "Garra não pegou",
            "type": "error",
            "date": 1626453572
        },
        {
            "code": 3,
            "description": "Troca de turno",
            "type": "info",
            "date": 1628620508
        },
        {
            "code": 3,
            "description": "Troca de turno",
            "type": "info",
            "date": 1628622586
        },
        {
            "code": 1,
            "description": "Garra não pegou",
            "type": "error",
            "date": 1628622610
        },
        {
            "code": 1,
            "description": "Garra não pegou",
            "type": "error",
            "date": 1628622765
        },
        {
            "code": 1,
            "description": "Garra não pegou",
            "type": "error",
            "date": 1628622778
        },
        {
            "code": 1,
            "description": "Garra não pegou",
            "type": "error",
            "date": 1628622909
        },
        {
            "code": 1,
            "description": "Garra não pegou",
            "type": "error",
            "date": 1628622987
        },
        {
            "code": 1,
            "description": "Garra não pegou",
            "type": "error",
            "date": 1628623490
        },
        {
            "code": 1,
            "description": "Garra não pegou",
            "type": "error",
            "date": 1628623741
        },
        {
            "code": 3,
            "description": "Troca de turno",
            "type": "info",
            "date": 1628624111
        },
        {
            "code": 1,
            "description": "Garra não pegou",
            "type": "error",
            "date": 1628625456
        },
        {
            "code": 1,
            "description": "Garra não pegou",
            "type": "error",
            "date": 1628625473
        },
        {
            "code": 3,
            "description": "Troca de turno",
            "type": "info",
            "date": 1628625888
        },
        {
            "code": 3,
            "description": "Troca de turno",
            "type": "info",
            "date": 1628625977
        }
    ]
}